collegamento/__init__.py
collegamento/files_variant.py
collegamento/client_server/__init__.py
collegamento/client_server/client.py
collegamento/client_server/server.py
collegamento/client_server/utils.py
collegamento-0.3.0.dist-info/LICENSE
collegamento-0.3.0.dist-info/METADATA
collegamento-0.3.0.dist-info/WHEEL
collegamento-0.3.0.dist-info/top_level.txt
collegamento-0.3.0.dist-info/RECORD
