Metadata-Version: 2.1
Name: collegamento
Version: 0.3.0
Summary: Collegamento provides an easy to use Client/Server IPC backend
Home-page: https://github.com/salve-org/collegamento
Author: Moosems
Author-email: moosems.j@gmail.com
License: MIT license
Classifier: Operating System :: OS Independent
Classifier: Programming Language :: Python :: Implementation
Classifier: Intended Audience :: Developers
Classifier: License :: OSI Approved :: MIT License
Classifier: Typing :: Typed
Requires-Python: >=3.11
License-File: LICENSE
Requires-Dist: beartype
